imitator/__init__.py
imitator/monitor.py
imitator/py.typed
imitator/storage.py
imitator/types.py
imitator-0.2.0.dist-info/licenses/LICENSE
imitator-0.2.0.dist-info/METADATA
imitator-0.2.0.dist-info/WHEEL
imitator-0.2.0.dist-info/top_level.txt
imitator-0.2.0.dist-info/RECORD
