Metadata-Version: 2.4
Name: imitator
Version: 0.2.0
Summary: A lightweight Python framework for monitoring and imitating function behavior with automatic I/O tracking and pattern learning
Author-email: Imitator Team <contact@imitator.dev>
Maintainer-email: Imitator Team <contact@imitator.dev>
License-Expression: Apache-2.0
Project-URL: Homepage, https://github.com/bhavikr2/imitator.git
Project-URL: Documentation, https://github.com/bhavikr2/imitator.git#readme
Project-URL: Repository, https://github.com/bhavikr2/imitator.git
Project-URL: Issues, https://github.com/bhavikr2/imitator.git/issues
Project-URL: Changelog, https://github.com/bhavikr2/imitator/blob/c4a45cfdaebccbd888ab12bdd2a7d3bced9ba61e/CHANGELOG.md
Keywords: monitoring,imitation,function,behavior,io,machine-learning,debugging,profiling,type-validation,decorator,pattern-learning
Classifier: Development Status :: 4 - Beta
Classifier: Intended Audience :: Developers
Classifier: Operating System :: OS Independent
Classifier: Programming Language :: Python :: 3
Classifier: Programming Language :: Python :: 3.8
Classifier: Programming Language :: Python :: 3.9
Classifier: Programming Language :: Python :: 3.10
Classifier: Programming Language :: Python :: 3.11
Classifier: Programming Language :: Python :: 3.12
Classifier: Topic :: Software Development :: Libraries :: Python Modules
Classifier: Topic :: Software Development :: Debuggers
Classifier: Topic :: System :: Monitoring
Classifier: Topic :: Scientific/Engineering :: Artificial Intelligence
Classifier: Typing :: Typed
Requires-Python: >=3.8
License-File: LICENSE
Requires-Dist: pydantic>=2.0.0
Provides-Extra: dev
Requires-Dist: pytest>=7.0.0; extra == "dev"
Requires-Dist: pytest-asyncio>=0.20.0; extra == "dev"
Requires-Dist: black>=23.0.0; extra == "dev"
Requires-Dist: flake8>=6.0.0; extra == "dev"
Requires-Dist: mypy>=1.0.0; extra == "dev"
Requires-Dist: pre-commit>=3.0.0; extra == "dev"
Provides-Extra: docs
Requires-Dist: mkdocs>=1.5.0; extra == "docs"
Requires-Dist: mkdocs-material>=9.0.0; extra == "docs"
Requires-Dist: mkdocstrings[python]>=0.24.0; extra == "docs"
Dynamic: license-file
